il13pred/Data/AAIndexNames.csv
il13pred/Data/Grantham.csv
il13pred/Data/PhysicoChemical.csv
il13pred/Data/Schneider-Wrede.csv
il13pred/Data/aa_attr_group.csv
il13pred/Data/aaind.txt
il13pred/Data/aaindex.csv
il13pred/Data/aaindices.csv
il13pred/Data/atom.csv
il13pred/Data/bin_di.csv
il13pred/Data/bonds.csv
il13pred/Data/can_pat.csv
il13pred/Data/data
il13pred/Data/z_aaindex.csv
il13pred/model/XGB_model
il13pred/python_scripts/__init__.py
il13pred/python_scripts/il13pred.py
il13pred-1.1.dist-info/LICENSE.txt
il13pred-1.1.dist-info/METADATA
il13pred-1.1.dist-info/WHEEL
il13pred-1.1.dist-info/entry_points.txt
il13pred-1.1.dist-info/top_level.txt
il13pred-1.1.dist-info/RECORD
