Metadata-Version: 2.1
Name: il13pred
Version: 1.1
Summary: A tool for predicting immunoregulatory cytokine IL-13 inducing peptides
Home-page: https://github.com/raghavagps/il13pred
Requires-Python: >=3.6
License-File: LICENSE.txt
Requires-Dist: numpy
Requires-Dist: pandas
Requires-Dist: argparse
Requires-Dist: xgboost (==1.4.0)
Requires-Dist: tqdm
